setup.cfg
setup.py
wharfee/__init__.py
wharfee/client.py
wharfee/completer.py
wharfee/config.py
wharfee/decorators.py
wharfee/formatter.py
wharfee/helpers.py
wharfee/keys.py
wharfee/lexer.py
wharfee/logger.py
wharfee/main.py
wharfee/option.py
wharfee/options.py
wharfee/style.py
wharfee/toolbar.py
wharfee/utils.py
wharfee/wharfeerc
wharfee.egg-info/PKG-INFO
wharfee.egg-info/SOURCES.txt
wharfee.egg-info/dependency_links.txt
wharfee.egg-info/entry_points.txt
wharfee.egg-info/pbr.json
wharfee.egg-info/requires.txt
wharfee.egg-info/top_level.txt