Metadata-Version: 1.1
Name: wharfee
Version: 0.7
Summary: Wharfee: a shell for Docker
Home-page: http://wharfee.com
Author: Iryna Cherniavska
Author-email: i[dot]chernyavska[at]gmail[dot]com
License: LICENSE.txt
Download-URL: http://github.com/j-bennet/wharfee
Platform: UNKNOWN
Classifier: Intended Audience :: Developers
Classifier: License :: OSI Approved :: BSD License
Classifier: Operating System :: Unix
Classifier: Programming Language :: Python
Classifier: Programming Language :: Python :: 2.7
Classifier: Programming Language :: Python :: 3
Classifier: Programming Language :: Python :: 3.3
Classifier: Programming Language :: Python :: 3.4
Classifier: Topic :: Software Development
Classifier: Topic :: Software Development :: Libraries :: Python Modules
